apply_subs/__init__.py
apply_subs/__main__.py
apply_subs/main.py
apply_subs-0.5.5.dist-info/LICENSE
apply_subs-0.5.5.dist-info/METADATA
apply_subs-0.5.5.dist-info/WHEEL
apply_subs-0.5.5.dist-info/entry_points.txt
apply_subs-0.5.5.dist-info/top_level.txt
apply_subs-0.5.5.dist-info/RECORD
