Metadata-Version: 2.1
Name: apply-subs
Version: 0.5.5
Summary: A command line tool to apply substitutions to a text file
Home-page: https://github.com/neutrinoceros/apply_subs
Author: C.M.T. Robert
License: GPL-3.0
Platform: UNKNOWN
Classifier: License :: OSI Approved :: GNU General Public License v3 (GPLv3)
Classifier: Programming Language :: Python :: 3
Classifier: Programming Language :: Python :: 3 :: Only
Classifier: Programming Language :: Python :: 3.7
Classifier: Programming Language :: Python :: 3.8
Classifier: Programming Language :: Python :: 3.9
Requires-Python: >=3.7
Requires-Dist: more-itertools (>=8.7.0)
Requires-Dist: rich (>=9.10.0)
Requires-Dist: schema (>=0.7.4)
